CHANGES.txt
COPYRIGHT.txt
LICENSE.txt
README.txt
bootstrap.py
buildout.cfg
setup.py
src/z3c/__init__.py
src/z3c.recipe.dev.egg-info/PKG-INFO
src/z3c.recipe.dev.egg-info/SOURCES.txt
src/z3c.recipe.dev.egg-info/dependency_links.txt
src/z3c.recipe.dev.egg-info/entry_points.txt
src/z3c.recipe.dev.egg-info/namespace_packages.txt
src/z3c.recipe.dev.egg-info/requires.txt
src/z3c.recipe.dev.egg-info/top_level.txt
src/z3c/recipe/__init__.py
src/z3c/recipe/dev/README.txt
src/z3c/recipe/dev/__init__.py
src/z3c/recipe/dev/app.py
src/z3c/recipe/dev/mkdir.py
src/z3c/recipe/dev/mkfile.py
src/z3c/recipe/dev/script.py
src/z3c/recipe/dev/tests.py