Metadata-Version: 1.0
Name: z3c.recipe.dev
Version: 0.6.0
Summary: Zope3 development server setup recipes
Home-page: http://pypi.python.org/pypi/z3c.recipe.dev
Author: Roger Ineichen and the Zope Community
Author-email: zope-dev@zope.org
License: ZPL 2.1
Keywords: zope3 z3c dev recipe
Platform: UNKNOWN
Classifier: Development Status :: 3 - Alpha
Classifier: Environment :: Web Environment
Classifier: Intended Audience :: Developers
Classifier: License :: OSI Approved :: Zope Public License
Classifier: Programming Language :: Python
Classifier: Natural Language :: English
Classifier: Operating System :: OS Independent
Classifier: Topic :: Internet :: WWW/HTTP
Classifier: Framework :: Zope3
